agentia/__init__.py
agentia/agent.py
agentia/history.py
agentia/llm/__init__.py
agentia/llm/completion.py
agentia/llm/stream.py
agentia/llm/providers/__init__.py
agentia/llm/providers/_openai_api.py
agentia/llm/providers/chutes.py
agentia/llm/providers/fireworks.py
agentia/llm/providers/gateway.py
agentia/llm/providers/ollama.py
agentia/llm/providers/openai.py
agentia/llm/providers/openrouter.py
agentia/llm/providers/qwen.py
agentia/plugins/__init__.py
agentia/plugins/calc.py
agentia/plugins/clock.py
agentia/plugins/code.py
agentia/plugins/memory.py
agentia/plugins/search.py
agentia/plugins/web.py
agentia/spec/__init__.py
agentia/spec/base.py
agentia/spec/chat.py
agentia/spec/stream.py
agentia/tools/__init__.py
agentia/tools/mcp.py
agentia/tools/plugin.py
agentia/tools/tools.py
agentia/utils/__init__.py
agentia/utils/config.py
agentia/utils/decorators.py
agentia-0.1.15.dist-info/METADATA
agentia-0.1.15.dist-info/WHEEL
agentia-0.1.15.dist-info/licenses/LICENSE
agentia-0.1.15.dist-info/RECORD
