Metadata-Version: 2.4
Name: agentia
Version: 0.1.15
Summary: Ergonomic LLM Agents
Project-URL: Repository, https://github.com/wenyuzhao/agentia
Author-email: Wenyu Zhao <wenyuzhaox@gmail.com>
License-Expression: MIT
License-File: LICENSE
Keywords: agent,ai-sdk,chatgpt,gpt,llm,openai,openrouter,tools
Requires-Python: >=3.12
Requires-Dist: filelock>=3.18.0
Requires-Dist: mcp>=1.12.0
Requires-Dist: nest-asyncio>=1.6.0
Requires-Dist: openai<2,>=1.108.1
Requires-Dist: pillow>=11.2.1
Requires-Dist: pydantic>=2.10.4
Requires-Dist: python-dotenv<2,>=1.0.0
Requires-Dist: websockets>=15.0.1
Provides-Extra: all
Requires-Dist: markdownify>=1.1.0; extra == 'all'
Requires-Dist: tavily-python>=0.7.12; extra == 'all'
Provides-Extra: plugins
Requires-Dist: markdownify>=1.1.0; extra == 'plugins'
Requires-Dist: tavily-python>=0.7.12; extra == 'plugins'
